Workbook

Sheet Instruções
A1: ELOGA | Consultoria & Estratégias em Saúde
A2: Modelo de custos e despesas mensais — clínica de estética
A4: Como preencher
A5: 1. Na aba "Custos por mês", informe o ano/mês de cada coluna (formato AAAA-MM, ex.: 2026-09) na linha dos meses.
A6: 2. Digite o valor pago em cada item, mês a mês, em R$. Deixe em branco o que a clínica não tem. Pode usar as linhas "Outro" para itens próprios.
A7: 3. Não altere a coluna "Grupo no painel": é ela que diz em qual linha da DRE cada item entra.
A8: 4. A aba "Mensal (importar)" soma tudo sozinha, por grupo, e é a única aba que o painel lê. Não digite nela.
A9: 5. Salve o arquivo no Excel e, no ELOGA Analytics, vá em Importar planilhas → Planilha mensal e envie este arquivo.
A11: Regras importantes
A12: • Informe o valor efetivamente pago no mês (regime de caixa), sem centavos de arredondamento forçado.
A13: • Profissionais da assistência (repasse), taxas de cartão, impostos e insumos podem ser calculados automaticamente pelo painel (repasse cadastrado, controle do particular, notas fiscais, kit). Se preferir o valor automático, deixe esses grupos em branco.
A14: • Receita NÃO entra aqui: em clínica de estética ela vem da agenda importada × tabela de procedimentos e pacotes.
... A16: • Não inclua dados de pacientes.
A18: Grupo no painel | B18: Tipo | C18: O que entra
A19: Equipe administrativa e pró-labore | B19: Custo fixo | C19: Pró-labore dos sócios; Recepção e administrativo (salário + encargos); Gerência / coordenação; Benefícios (VT, VR, plano); 13º, férias e rescisões (provisão ou pago); Outro (equipe administrativa)
A20: Aluguel, condomínio e utilidades | B20: Custo fixo | C20: Aluguel; Condomínio; IPTU; Energia elétrica; Água e esgoto; Internet e telefone; Limpeza e zeladoria; Segurança e monitoramento; Outro (ocupação)
A21: Sistemas, marketing e outros fixos | B21: Custo fixo | C21: Sistema de gestão e agenda; Contabilidade; Marketing e tráfego pago; Manutenção e calibração de equipamentos; Seguros; Alvará, licenças e vigilância sanitária; Assinaturas (música, streaming, software); Outro fixo
A22: Insumos e materiais | B22: Custo variável | C22: Descartáveis (luvas, máscaras, lençóis, toucas); Cosméticos e ativos de uso profissional; Injetáveis e produtos de procedimento; Lavanderia e enxoval; Material de escritório e limpeza; Outro insumo
A23: Profissionais da assistência (repasse/folha) | B23: Custo variável | C23: Repasse a profissionais (esteticistas, biomédicos, fisioterapeutas); Folha de profissionais CLT da assistência; Outro (assistência)
A24: Comissões e outros variáveis (opcional) | B24: Custo variável | C24: Comissão por venda de pacote; Comissão por indicação; Brindes e cortesias; Outro variável
A25: Taxas de cartão e antecipação | B25: Custo variável | C25: Taxa de cartão (débito/crédito); Antecipação de recebíveis; Taxa de plataforma de pagamento / link
A26: Impostos pagos no mês (R$) | B26: Dedução | C26: DAS (Simples Nacional); ISS; PIS/COFINS e retenções; Outros tributos
A27: Descontos concedidos | B27: Dedução | C27: Descontos em pacotes e promoções; Cortesias e cancelamentos de cobrança
A28: Despesas financeiras | B28: Financeiro | C28: Juros e multas; Tarifas bancárias; IOF
A29: Parcelas de dívidas pagas no mês | B29: Caixa | C29: Parcela de empréstimo / financiamento; Parcela de equipamento financiado
... A31: Saldo de caixa no fim do mês | B31: Posição (informar o valor do fim do mês) | C31: Saldo em conta e aplicações de resgate imediato

Sheet Custos por mês
A1: Custos e despesas por mês (R$)
A2: Preencha as células amarelas. Altere os meses na linha 4 (AAAA-MM). Valores em R$.
A4: Grupo no painel | B4: Item | C4: Tipo | D4: 2026-01 | E4: 2026-02 | F4: 2026-03 | G4: 2026-04 | H4: 2026-05 | I4: 2026-06 | J4: 2026-07 | K4: 2026-08 | L4: 2026-09 | M4: 2026-10 | N4: 2026-11 | O4: 2026-12
A5: Equipe administrativa e pró-labore | B5: Pró-labore dos sócios | C5: Custo fixo
A6: Equipe administrativa e pró-labore | B6: Recepção e administrativo (salário + encargos) | C6: Custo fixo
A7: Equipe administrativa e pró-labore | B7: Gerência / coordenação | C7: Custo fixo
A8: Equipe administrativa e pró-labore | B8: Benefícios (VT, VR, plano) | C8: Custo fixo
A9: Equipe administrativa e pró-labore | B9: 13º, férias e rescisões (provisão ou pago) | C9: Custo fixo
A10: Equipe administrativa e pró-labore | B10: Outro (equipe administrativa) | C10: Custo fixo
A11: Aluguel, condomínio e utilidades | B11: Aluguel | C11: Custo fixo
A12: Aluguel, condomínio e utilidades | B12: Condomínio | C12: Custo fixo
A13: Aluguel, condomínio e utilidades | B13: IPTU | C13: Custo fixo
A14: Aluguel, condomínio e utilidades | B14: Energia elétrica | C14: Custo fixo
A15: Aluguel, condomínio e utilidades | B15: Água e esgoto | C15: Custo fixo
A16: Aluguel, condomínio e utilidades | B16: Internet e telefone | C16: Custo fixo
... A56: Saldo de caixa no fim do mês | B56: Saldo em conta e aplicações de resgate imediato | C56: Posição
B58: Total de saídas do mês (sem saldos) | D58: =SUMIF($C$5:$C$56,"<>Posição",D5:D56) | E58: =SUMIF($C$5:$C$56,"<>Posição",E5:E56) | F58: =SUMIF($C$5:$C$56,"<>Posição",F5:F56) | G58: =SUMIF($C$5:$C$56,"<>Posição",G5:G56) | H58: =SUMIF($C$5:$C$56,"<>Posição",H5:H56) | I58: =SUMIF($C$5:$C$56,"<>Posição",I5:I56) | J58: =SUMIF($C$5:$C$56,"<>Posição",J5:J56) | K58: =SUMIF($C$5:$C$56,"<>Posição",K5:K56) | ... O58: =SUMIF($C$5:$C$56,"<>Posição",O5:O56)

Sheet Mensal (importar)
A1: Competência | B1: Equipe administrativa e pró-labore | C1: Aluguel, condomínio e utilidades | D1: Sistemas, marketing e outros fixos | E1: Insumos e materiais | F1: Profissionais da assistência (repasse/folha) | G1: Comissões e outros variáveis (opcional) | H1: Taxas de cartão e antecipação | I1: Impostos pagos no mês (R$) | J1: Descontos concedidos | K1: Despesas financeiras | L1: Parcelas de dívidas pagas no mês | M1: Saldo devedor de empréstimos | N1: Saldo de caixa no fim do mês
A2: ='Custos por mês'!D4 | B2: =IF(SUMIF('Custos por mês'!$A$5:$A$56,"Equipe administrativa e pró-labore",'Custos por mês'!D$5:D$56)=0,"",SUMIF('Custos por mês'!$A$5:$A$56,"Equipe administrativa e pró-labore",'Custos por mês'!D$5:D$56)) | C2: =IF(SUMIF('Custos por mês'!$A$5:$A$56,"Aluguel, condomínio e utilidades",'Custos por mês'!D$5:D$56)=0,"",SUMIF('Custos por mês'!$A$5:$A$56,"Aluguel, condomínio e utilidades",'Custos por mês'!D$5:D$56)) | D2: =IF(SUMIF('Custos por mês'!$A$5:$A$56,"Sistemas, marketing e outros fixos",'Custos por mês'!D$5:D$56)=0,"",SUMIF('Custos por mês'!$A$5:$A$56,"Sistemas, marketing e outros fixos",'Custos por mês'!D$5:D$56)) | E2: =IF(SUMIF('Custos por mês'!$A$5:$A$56,"Insumos e materiais",'Custos por mês'!D$5:D$56)=0,"",SUMIF('Custos por mês'!$A$5:$A$56,"Insumos e materiais",'Custos por mês'!D$5:D$56)) | F2: =IF(SUMIF('Custos por mês'!$A$5:$A$56,"Profissionais da assistência (repasse/folha)",'Custos por mês'!D$5:D$56)=0,"",SUMIF('Custos por mês'!$A$5:$A$56,"Profissionais da assistência (repasse/folha)",'Custos por mês'!D$5:D$56)) | G2: =IF(SUMIF('Custos por mês'!$A$5:$A$56,"Comissões e outros variáveis (opcional)",'Custos por mês'!D$5:D$56)=0,"",SUMIF('Custos por mês'!$A$5:$A$56,"Comissões e outros variáveis (opcional)",'Custos por mês'!D$5:D$56)) | H2: =IF(SUMIF('Custos por mês'!$A$5:$A$56,"Taxas de cartão e antecipação",'Custos por mês'!D$5:D$56)=0,"",SUMIF('Custos por mês'!$A$5:$A$56,"Taxas de cartão e antecipação",'Custos por mês'!D$5:D$56)) | I2: =IF(SUMIF('Custos por mês'!$A$5:$A$56,"Impostos pagos no mês (R$)",'Custos por mês'!D$5:D$56)=0,"",SUMIF('Custos por mês'!$A$5:$A$56,"Impostos pagos no mês (R$)",'Custos por mês'!D$5:D$56)) | J2: =IF(SUMIF('Custos por mês'!$A$5:$A$56,"Descontos concedidos",'Custos por mês'!D$5:D$56)=0,"",SUMIF('Custos por mês'!$A$5:$A$56,"Descontos concedidos",'Custos por mês'!D$5:D$56)) | K2: =IF(SUMIF('Custos por mês'!$A$5:$A$56,"Despesas financeiras",'Custos por mês'!D$5:D$56)=0,"",SUMIF('Custos por mês'!$A$5:$A$56,"Despesas financeiras",'Custos por mês'!D$5:D$56)) | L2: =IF(SUMIF('Custos por mês'!$A$5:$A$56,"Parcelas de dívidas pagas no mês",'Custos por mês'!D$5:D$56)=0,"",SUMIF('Custos por mês'!$A$5:$A$56,"Parcelas de dívidas pagas no mês",'Custos por mês'!D$5:D$56)) | M2: =IF(SUMIF('Custos por mês'!$A$5:$A$56,"Saldo devedor de empréstimos",'Custos por mês'!D$5:D$56)=0,"",SUMIF('Custos por mês'!$A$5:$A$56,"Saldo devedor de empréstimos",'Custos por mês'!D$5:D$56)) | N2: =IF(SUMIF('Custos por mês'!$A$5:$A$56,"Saldo de caixa no fim do mês",'Custos por mês'!D$5:D$56)=0,"",SUMIF('Custos por mês'!$A$5:$A$56,"Saldo de caixa no fim do mês",'Custos por mês'!D$5:D$56))
A3: ='Custos por mês'!E4 | B3: =IF(SUMIF('Custos por mês'!$A$5:$A$56,"Equipe administrativa e pró-labore",'Custos por mês'!E$5:E$56)=0,"",SUMIF('Custos por mês'!$A$5:$A$56,"Equipe administrativa e pró-labore",'Custos por mês'!E$5:E$56)) | C3: =IF(SUMIF('Custos por mês'!$A$5:$A$56,"Aluguel, condomínio e utilidades",'Custos por mês'!E$5:E$56)=0,"",SUMIF('Custos por mês'!$A$5:$A$56,"Aluguel, condomínio e utilidades",'Custos por mês'!E$5:E$56)) | D3: =IF(SUMIF('Custos por mês'!$A$5:$A$56,"Sistemas, marketing e outros fixos",'Custos por mês'!E$5:E$56)=0,"",SUMIF('Custos por mês'!$A$5:$A$56,"Sistemas, marketing e outros fixos",'Custos por mês'!E$5:E$56)) | E3: =IF(SUMIF('Custos por mês'!$A$5:$A$56,"Insumos e materiais",'Custos por mês'!E$5:E$56)=0,"",SUMIF('Custos por mês'!$A$5:$A$56,"Insumos e materiais",'Custos por mês'!E$5:E$56)) | F3: =IF(SUMIF('Custos por mês'!$A$5:$A$56,"Profissionais da assistência (repasse/folha)",'Custos por mês'!E$5:E$56)=0,"",SUMIF('Custos por mês'!$A$5:$A$56,"Profissionais da assistência (repasse/folha)",'Custos por mês'!E$5:E$56)) | G3: =IF(SUMIF('Custos por mês'!$A$5:$A$56,"Comissões e outros variáveis (opcional)",'Custos por mês'!E$5:E$56)=0,"",SUMIF('Custos por mês'!$A$5:$A$56,"Comissões e outros variáveis (opcional)",'Custos por mês'!E$5:E$56)) | H3: =IF(SUMIF('Custos por mês'!$A$5:$A$56,"Taxas de cartão e antecipação",'Custos por mês'!E$5:E$56)=0,"",SUMIF('Custos por mês'!$A$5:$A$56,"Taxas de cartão e antecipação",'Custos por mês'!E$5:E$56)) | I3: =IF(SUMIF('Custos por mês'!$A$5:$A$56,"Impostos pagos no mês (R$)",'Custos por mês'!E$5:E$56)=0,"",SUMIF('Custos por mês'!$A$5:$A$56,"Impostos pagos no mês (R$)",'Custos por mês'!E$5:E$56)) | J3: =IF(SUMIF('Custos por mês'!$A$5:$A$56,"Descontos concedidos",'Custos por mês'!E$5:E$56)=0,"",SUMIF('Custos por mês'!$A$5:$A$56,"Descontos concedidos",'Custos por mês'!E$5:E$56)) | K3: =IF(SUMIF('Custos por mês'!$A$5:$A$56,"Despesas financeiras",'Custos por mês'!E$5:E$56)=0,"",SUMIF('Custos por mês'!$A$5:$A$56,"Despesas financeiras",'Custos por mês'!E$5:E$56)) | L3: =IF(SUMIF('Custos por mês'!$A$5:$A$56,"Parcelas de dívidas pagas no mês",'Custos por mês'!E$5:E$56)=0,"",SUMIF('Custos por mês'!$A$5:$A$56,"Parcelas de dívidas pagas no mês",'Custos por mês'!E$5:E$56)) | M3: =IF(SUMIF('Custos por mês'!$A$5:$A$56,"Saldo devedor de empréstimos",'Custos por mês'!E$5:E$56)=0,"",SUMIF('Custos por mês'!$A$5:$A$56,"Saldo devedor de empréstimos",'Custos por mês'!E$5:E$56)) | N3: =IF(SUMIF('Custos por mês'!$A$5:$A$56,"Saldo de caixa no fim do mês",'Custos por mês'!E$5:E$56)=0,"",SUMIF('Custos por mês'!$A$5:$A$56,"Saldo de caixa no fim do mês",'Custos por mês'!E$5:E$56))
A4: ='Custos por mês'!F4 | B4: =IF(SUMIF('Custos por mês'!$A$5:$A$56,"Equipe administrativa e pró-labore",'Custos por mês'!F$5:F$56)=0,"",SUMIF('Custos por mês'!$A$5:$A$56,"Equipe administrativa e pró-labore",'Custos por mês'!F$5:F$56)) | C4: =IF(SUMIF('Custos por mês'!$A$5:$A$56,"Aluguel, condomínio e utilidades",'Custos por mês'!F$5:F$56)=0,"",SUMIF('Custos por mês'!$A$5:$A$56,"Aluguel, condomínio e utilidades",'Custos por mês'!F$5:F$56)) | D4: =IF(SUMIF('Custos por mês'!$A$5:$A$56,"Sistemas, marketing e outros fixos",'Custos por mês'!F$5:F$56)=0,"",SUMIF('Custos por mês'!$A$5:$A$56,"Sistemas, marketing e outros fixos",'Custos por mês'!F$5:F$56)) | E4: =IF(SUMIF('Custos por mês'!$A$5:$A$56,"Insumos e materiais",'Custos por mês'!F$5:F$56)=0,"",SUMIF('Custos por mês'!$A$5:$A$56,"Insumos e materiais",'Custos por mês'!F$5:F$56)) | F4: =IF(SUMIF('Custos por mês'!$A$5:$A$56,"Profissionais da assistência (repasse/folha)",'Custos por mês'!F$5:F$56)=0,"",SUMIF('Custos por mês'!$A$5:$A$56,"Profissionais da assistência (repasse/folha)",'Custos por mês'!F$5:F$56)) | G4: =IF(SUMIF('Custos por mês'!$A$5:$A$56,"Comissões e outros variáveis (opcional)",'Custos por mês'!F$5:F$56)=0,"",SUMIF('Custos por mês'!$A$5:$A$56,"Comissões e outros variáveis (opcional)",'Custos por mês'!F$5:F$56)) | H4: =IF(SUMIF('Custos por mês'!$A$5:$A$56,"Taxas de cartão e antecipação",'Custos por mês'!F$5:F$56)=0,"",SUMIF('Custos por mês'!$A$5:$A$56,"Taxas de cartão e antecipação",'Custos por mês'!F$5:F$56)) | I4: =IF(SUMIF('Custos por mês'!$A$5:$A$56,"Impostos pagos no mês (R$)",'Custos por mês'!F$5:F$56)=0,"",SUMIF('Custos por mês'!$A$5:$A$56,"Impostos pagos no mês (R$)",'Custos por mês'!F$5:F$56)) | J4: =IF(SUMIF('Custos por mês'!$A$5:$A$56,"Descontos concedidos",'Custos por mês'!F$5:F$56)=0,"",SUMIF('Custos por mês'!$A$5:$A$56,"Descontos concedidos",'Custos por mês'!F$5:F$56)) | K4: =IF(SUMIF('Custos por mês'!$A$5:$A$56,"Despesas financeiras",'Custos por mês'!F$5:F$56)=0,"",SUMIF('Custos por mês'!$A$5:$A$56,"Despesas financeiras",'Custos por mês'!F$5:F$56)) | L4: =IF(SUMIF('Custos por mês'!$A$5:$A$56,"Parcelas de dívidas pagas no mês",'Custos por mês'!F$5:F$56)=0,"",SUMIF('Custos por mês'!$A$5:$A$56,"Parcelas de dívidas pagas no mês",'Custos por mês'!F$5:F$56)) | M4: =IF(SUMIF('Custos por mês'!$A$5:$A$56,"Saldo devedor de empréstimos",'Custos por mês'!F$5:F$56)=0,"",SUMIF('Custos por mês'!$A$5:$A$56,"Saldo devedor de empréstimos",'Custos por mês'!F$5:F$56)) | N4: =IF(SUMIF('Custos por mês'!$A$5:$A$56,"Saldo de caixa no fim do mês",'Custos por mês'!F$5:F$56)=0,"",SUMIF('Custos por mês'!$A$5:$A$56,"Saldo de caixa no fim do mês",'Custos por mês'!F$5:F$56))
A5: ='Custos por mês'!G4 | B5: =IF(SUMIF('Custos por mês'!$A$5:$A$56,"Equipe administrativa e pró-labore",'Custos por mês'!G$5:G$56)=0,"",SUMIF('Custos por mês'!$A$5:$A$56,"Equipe administrativa e pró-labore",'Custos por mês'!G$5:G$56)) | C5: =IF(SUMIF('Custos por mês'!$A$5:$A$56,"Aluguel, condomínio e utilidades",'Custos por mês'!G$5:G$56)=0,"",SUMIF('Custos por mês'!$A$5:$A$56,"Aluguel, condomínio e utilidades",'Custos por mês'!G$5:G$56)) | D5: =IF(SUMIF('Custos por mês'!$A$5:$A$56,"Sistemas, marketing e outros fixos",'Custos por mês'!G$5:G$56)=0,"",SUMIF('Custos por mês'!$A$5:$A$56,"Sistemas, marketing e outros fixos",'Custos por mês'!G$5:G$56)) | E5: =IF(SUMIF('Custos por mês'!$A$5:$A$56,"Insumos e materiais",'Custos por mês'!G$5:G$56)=0,"",SUMIF('Custos por mês'!$A$5:$A$56,"Insumos e materiais",'Custos por mês'!G$5:G$56)) | F5: =IF(SUMIF('Custos por mês'!$A$5:$A$56,"Profissionais da assistência (repasse/folha)",'Custos por mês'!G$5:G$56)=0,"",SUMIF('Custos por mês'!$A$5:$A$56,"Profissionais da assistência (repasse/folha)",'Custos por mês'!G$5:G$56)) | G5: =IF(SUMIF('Custos por mês'!$A$5:$A$56,"Comissões e outros variáveis (opcional)",'Custos por mês'!G$5:G$56)=0,"",SUMIF('Custos por mês'!$A$5:$A$56,"Comissões e outros variáveis (opcional)",'Custos por mês'!G$5:G$56)) | H5: =IF(SUMIF('Custos por mês'!$A$5:$A$56,"Taxas de cartão e antecipação",'Custos por mês'!G$5:G$56)=0,"",SUMIF('Custos por mês'!$A$5:$A$56,"Taxas de cartão e antecipação",'Custos por mês'!G$5:G$56)) | I5: =IF(SUMIF('Custos por mês'!$A$5:$A$56,"Impostos pagos no mês (R$)",'Custos por mês'!G$5:G$56)=0,"",SUMIF('Custos por mês'!$A$5:$A$56,"Impostos pagos no mês (R$)",'Custos por mês'!G$5:G$56)) | J5: =IF(SUMIF('Custos por mês'!$A$5:$A$56,"Descontos concedidos",'Custos por mês'!G$5:G$56)=0,"",SUMIF('Custos por mês'!$A$5:$A$56,"Descontos concedidos",'Custos por mês'!G$5:G$56)) | K5: =IF(SUMIF('Custos por mês'!$A$5:$A$56,"Despesas financeiras",'Custos por mês'!G$5:G$56)=0,"",SUMIF('Custos por mês'!$A$5:$A$56,"Despesas financeiras",'Custos por mês'!G$5:G$56)) | L5: =IF(SUMIF('Custos por mês'!$A$5:$A$56,"Parcelas de dívidas pagas no mês",'Custos por mês'!G$5:G$56)=0,"",SUMIF('Custos por mês'!$A$5:$A$56,"Parcelas de dívidas pagas no mês",'Custos por mês'!G$5:G$56)) | M5: =IF(SUMIF('Custos por mês'!$A$5:$A$56,"Saldo devedor de empréstimos",'Custos por mês'!G$5:G$56)=0,"",SUMIF('Custos por mês'!$A$5:$A$56,"Saldo devedor de empréstimos",'Custos por mês'!G$5:G$56)) | N5: =IF(SUMIF('Custos por mês'!$A$5:$A$56,"Saldo de caixa no fim do mês",'Custos por mês'!G$5:G$56)=0,"",SUMIF('Custos por mês'!$A$5:$A$56,"Saldo de caixa no fim do mês",'Custos por mês'!G$5:G$56))
A6: ='Custos por mês'!H4 | B6: =IF(SUMIF('Custos por mês'!$A$5:$A$56,"Equipe administrativa e pró-labore",'Custos por mês'!H$5:H$56)=0,"",SUMIF('Custos por mês'!$A$5:$A$56,"Equipe administrativa e pró-labore",'Custos por mês'!H$5:H$56)) | C6: =IF(SUMIF('Custos por mês'!$A$5:$A$56,"Aluguel, condomínio e utilidades",'Custos por mês'!H$5:H$56)=0,"",SUMIF('Custos por mês'!$A$5:$A$56,"Aluguel, condomínio e utilidades",'Custos por mês'!H$5:H$56)) | D6: =IF(SUMIF('Custos por mês'!$A$5:$A$56,"Sistemas, marketing e outros fixos",'Custos por mês'!H$5:H$56)=0,"",SUMIF('Custos por mês'!$A$5:$A$56,"Sistemas, marketing e outros fixos",'Custos por mês'!H$5:H$56)) | E6: =IF(SUMIF('Custos por mês'!$A$5:$A$56,"Insumos e materiais",'Custos por mês'!H$5:H$56)=0,"",SUMIF('Custos por mês'!$A$5:$A$56,"Insumos e materiais",'Custos por mês'!H$5:H$56)) | F6: =IF(SUMIF('Custos por mês'!$A$5:$A$56,"Profissionais da assistência (repasse/folha)",'Custos por mês'!H$5:H$56)=0,"",SUMIF('Custos por mês'!$A$5:$A$56,"Profissionais da assistência (repasse/folha)",'Custos por mês'!H$5:H$56)) | G6: =IF(SUMIF('Custos por mês'!$A$5:$A$56,"Comissões e outros variáveis (opcional)",'Custos por mês'!H$5:H$56)=0,"",SUMIF('Custos por mês'!$A$5:$A$56,"Comissões e outros variáveis (opcional)",'Custos por mês'!H$5:H$56)) | H6: =IF(SUMIF('Custos por mês'!$A$5:$A$56,"Taxas de cartão e antecipação",'Custos por mês'!H$5:H$56)=0,"",SUMIF('Custos por mês'!$A$5:$A$56,"Taxas de cartão e antecipação",'Custos por mês'!H$5:H$56)) | I6: =IF(SUMIF('Custos por mês'!$A$5:$A$56,"Impostos pagos no mês (R$)",'Custos por mês'!H$5:H$56)=0,"",SUMIF('Custos por mês'!$A$5:$A$56,"Impostos pagos no mês (R$)",'Custos por mês'!H$5:H$56)) | J6: =IF(SUMIF('Custos por mês'!$A$5:$A$56,"Descontos concedidos",'Custos por mês'!H$5:H$56)=0,"",SUMIF('Custos por mês'!$A$5:$A$56,"Descontos concedidos",'Custos por mês'!H$5:H$56)) | K6: =IF(SUMIF('Custos por mês'!$A$5:$A$56,"Despesas financeiras",'Custos por mês'!H$5:H$56)=0,"",SUMIF('Custos por mês'!$A$5:$A$56,"Despesas financeiras",'Custos por mês'!H$5:H$56)) | L6: =IF(SUMIF('Custos por mês'!$A$5:$A$56,"Parcelas de dívidas pagas no mês",'Custos por mês'!H$5:H$56)=0,"",SUMIF('Custos por mês'!$A$5:$A$56,"Parcelas de dívidas pagas no mês",'Custos por mês'!H$5:H$56)) | M6: =IF(SUMIF('Custos por mês'!$A$5:$A$56,"Saldo devedor de empréstimos",'Custos por mês'!H$5:H$56)=0,"",SUMIF('Custos por mês'!$A$5:$A$56,"Saldo devedor de empréstimos",'Custos por mês'!H$5:H$56)) | N6: =IF(SUMIF('Custos por mês'!$A$5:$A$56,"Saldo de caixa no fim do mês",'Custos por mês'!H$5:H$56)=0,"",SUMIF('Custos por mês'!$A$5:$A$56,"Saldo de caixa no fim do mês",'Custos por mês'!H$5:H$56))
A7: ='Custos por mês'!I4 | B7: =IF(SUMIF('Custos por mês'!$A$5:$A$56,"Equipe administrativa e pró-labore",'Custos por mês'!I$5:I$56)=0,"",SUMIF('Custos por mês'!$A$5:$A$56,"Equipe administrativa e pró-labore",'Custos por mês'!I$5:I$56)) | C7: =IF(SUMIF('Custos por mês'!$A$5:$A$56,"Aluguel, condomínio e utilidades",'Custos por mês'!I$5:I$56)=0,"",SUMIF('Custos por mês'!$A$5:$A$56,"Aluguel, condomínio e utilidades",'Custos por mês'!I$5:I$56)) | D7: =IF(SUMIF('Custos por mês'!$A$5:$A$56,"Sistemas, marketing e outros fixos",'Custos por mês'!I$5:I$56)=0,"",SUMIF('Custos por mês'!$A$5:$A$56,"Sistemas, marketing e outros fixos",'Custos por mês'!I$5:I$56)) | E7: =IF(SUMIF('Custos por mês'!$A$5:$A$56,"Insumos e materiais",'Custos por mês'!I$5:I$56)=0,"",SUMIF('Custos por mês'!$A$5:$A$56,"Insumos e materiais",'Custos por mês'!I$5:I$56)) | F7: =IF(SUMIF('Custos por mês'!$A$5:$A$56,"Profissionais da assistência (repasse/folha)",'Custos por mês'!I$5:I$56)=0,"",SUMIF('Custos por mês'!$A$5:$A$56,"Profissionais da assistência (repasse/folha)",'Custos por mês'!I$5:I$56)) | G7: =IF(SUMIF('Custos por mês'!$A$5:$A$56,"Comissões e outros variáveis (opcional)",'Custos por mês'!I$5:I$56)=0,"",SUMIF('Custos por mês'!$A$5:$A$56,"Comissões e outros variáveis (opcional)",'Custos por mês'!I$5:I$56)) | H7: =IF(SUMIF('Custos por mês'!$A$5:$A$56,"Taxas de cartão e antecipação",'Custos por mês'!I$5:I$56)=0,"",SUMIF('Custos por mês'!$A$5:$A$56,"Taxas de cartão e antecipação",'Custos por mês'!I$5:I$56)) | I7: =IF(SUMIF('Custos por mês'!$A$5:$A$56,"Impostos pagos no mês (R$)",'Custos por mês'!I$5:I$56)=0,"",SUMIF('Custos por mês'!$A$5:$A$56,"Impostos pagos no mês (R$)",'Custos por mês'!I$5:I$56)) | J7: =IF(SUMIF('Custos por mês'!$A$5:$A$56,"Descontos concedidos",'Custos por mês'!I$5:I$56)=0,"",SUMIF('Custos por mês'!$A$5:$A$56,"Descontos concedidos",'Custos por mês'!I$5:I$56)) | K7: =IF(SUMIF('Custos por mês'!$A$5:$A$56,"Despesas financeiras",'Custos por mês'!I$5:I$56)=0,"",SUMIF('Custos por mês'!$A$5:$A$56,"Despesas financeiras",'Custos por mês'!I$5:I$56)) | L7: =IF(SUMIF('Custos por mês'!$A$5:$A$56,"Parcelas de dívidas pagas no mês",'Custos por mês'!I$5:I$56)=0,"",SUMIF('Custos por mês'!$A$5:$A$56,"Parcelas de dívidas pagas no mês",'Custos por mês'!I$5:I$56)) | M7: =IF(SUMIF('Custos por mês'!$A$5:$A$56,"Saldo devedor de empréstimos",'Custos por mês'!I$5:I$56)=0,"",SUMIF('Custos por mês'!$A$5:$A$56,"Saldo devedor de empréstimos",'Custos por mês'!I$5:I$56)) | N7: =IF(SUMIF('Custos por mês'!$A$5:$A$56,"Saldo de caixa no fim do mês",'Custos por mês'!I$5:I$56)=0,"",SUMIF('Custos por mês'!$A$5:$A$56,"Saldo de caixa no fim do mês",'Custos por mês'!I$5:I$56))
A8: ='Custos por mês'!J4 | B8: =IF(SUMIF('Custos por mês'!$A$5:$A$56,"Equipe administrativa e pró-labore",'Custos por mês'!J$5:J$56)=0,"",SUMIF('Custos por mês'!$A$5:$A$56,"Equipe administrativa e pró-labore",'Custos por mês'!J$5:J$56)) | C8: =IF(SUMIF('Custos por mês'!$A$5:$A$56,"Aluguel, condomínio e utilidades",'Custos por mês'!J$5:J$56)=0,"",SUMIF('Custos por mês'!$A$5:$A$56,"Aluguel, condomínio e utilidades",'Custos por mês'!J$5:J$56)) | D8: =IF(SUMIF('Custos por mês'!$A$5:$A$56,"Sistemas, marketing e outros fixos",'Custos por mês'!J$5:J$56)=0,"",SUMIF('Custos por mês'!$A$5:$A$56,"Sistemas, marketing e outros fixos",'Custos por mês'!J$5:J$56)) | E8: =IF(SUMIF('Custos por mês'!$A$5:$A$56,"Insumos e materiais",'Custos por mês'!J$5:J$56)=0,"",SUMIF('Custos por mês'!$A$5:$A$56,"Insumos e materiais",'Custos por mês'!J$5:J$56)) | F8: =IF(SUMIF('Custos por mês'!$A$5:$A$56,"Profissionais da assistência (repasse/folha)",'Custos por mês'!J$5:J$56)=0,"",SUMIF('Custos por mês'!$A$5:$A$56,"Profissionais da assistência (repasse/folha)",'Custos por mês'!J$5:J$56)) | G8: =IF(SUMIF('Custos por mês'!$A$5:$A$56,"Comissões e outros variáveis (opcional)",'Custos por mês'!J$5:J$56)=0,"",SUMIF('Custos por mês'!$A$5:$A$56,"Comissões e outros variáveis (opcional)",'Custos por mês'!J$5:J$56)) | H8: =IF(SUMIF('Custos por mês'!$A$5:$A$56,"Taxas de cartão e antecipação",'Custos por mês'!J$5:J$56)=0,"",SUMIF('Custos por mês'!$A$5:$A$56,"Taxas de cartão e antecipação",'Custos por mês'!J$5:J$56)) | I8: =IF(SUMIF('Custos por mês'!$A$5:$A$56,"Impostos pagos no mês (R$)",'Custos por mês'!J$5:J$56)=0,"",SUMIF('Custos por mês'!$A$5:$A$56,"Impostos pagos no mês (R$)",'Custos por mês'!J$5:J$56)) | J8: =IF(SUMIF('Custos por mês'!$A$5:$A$56,"Descontos concedidos",'Custos por mês'!J$5:J$56)=0,"",SUMIF('Custos por mês'!$A$5:$A$56,"Descontos concedidos",'Custos por mês'!J$5:J$56)) | K8: =IF(SUMIF('Custos por mês'!$A$5:$A$56,"Despesas financeiras",'Custos por mês'!J$5:J$56)=0,"",SUMIF('Custos por mês'!$A$5:$A$56,"Despesas financeiras",'Custos por mês'!J$5:J$56)) | L8: =IF(SUMIF('Custos por mês'!$A$5:$A$56,"Parcelas de dívidas pagas no mês",'Custos por mês'!J$5:J$56)=0,"",SUMIF('Custos por mês'!$A$5:$A$56,"Parcelas de dívidas pagas no mês",'Custos por mês'!J$5:J$56)) | M8: =IF(SUMIF('Custos por mês'!$A$5:$A$56,"Saldo devedor de empréstimos",'Custos por mês'!J$5:J$56)=0,"",SUMIF('Custos por mês'!$A$5:$A$56,"Saldo devedor de empréstimos",'Custos por mês'!J$5:J$56)) | N8: =IF(SUMIF('Custos por mês'!$A$5:$A$56,"Saldo de caixa no fim do mês",'Custos por mês'!J$5:J$56)=0,"",SUMIF('Custos por mês'!$A$5:$A$56,"Saldo de caixa no fim do mês",'Custos por mês'!J$5:J$56))
A9: ='Custos por mês'!K4 | B9: =IF(SUMIF('Custos por mês'!$A$5:$A$56,"Equipe administrativa e pró-labore",'Custos por mês'!K$5:K$56)=0,"",SUMIF('Custos por mês'!$A$5:$A$56,"Equipe administrativa e pró-labore",'Custos por mês'!K$5:K$56)) | C9: =IF(SUMIF('Custos por mês'!$A$5:$A$56,"Aluguel, condomínio e utilidades",'Custos por mês'!K$5:K$56)=0,"",SUMIF('Custos por mês'!$A$5:$A$56,"Aluguel, condomínio e utilidades",'Custos por mês'!K$5:K$56)) | D9: =IF(SUMIF('Custos por mês'!$A$5:$A$56,"Sistemas, marketing e outros fixos",'Custos por mês'!K$5:K$56)=0,"",SUMIF('Custos por mês'!$A$5:$A$56,"Sistemas, marketing e outros fixos",'Custos por mês'!K$5:K$56)) | E9: =IF(SUMIF('Custos por mês'!$A$5:$A$56,"Insumos e materiais",'Custos por mês'!K$5:K$56)=0,"",SUMIF('Custos por mês'!$A$5:$A$56,"Insumos e materiais",'Custos por mês'!K$5:K$56)) | F9: =IF(SUMIF('Custos por mês'!$A$5:$A$56,"Profissionais da assistência (repasse/folha)",'Custos por mês'!K$5:K$56)=0,"",SUMIF('Custos por mês'!$A$5:$A$56,"Profissionais da assistência (repasse/folha)",'Custos por mês'!K$5:K$56)) | G9: =IF(SUMIF('Custos por mês'!$A$5:$A$56,"Comissões e outros variáveis (opcional)",'Custos por mês'!K$5:K$56)=0,"",SUMIF('Custos por mês'!$A$5:$A$56,"Comissões e outros variáveis (opcional)",'Custos por mês'!K$5:K$56)) | H9: =IF(SUMIF('Custos por mês'!$A$5:$A$56,"Taxas de cartão e antecipação",'Custos por mês'!K$5:K$56)=0,"",SUMIF('Custos por mês'!$A$5:$A$56,"Taxas de cartão e antecipação",'Custos por mês'!K$5:K$56)) | I9: =IF(SUMIF('Custos por mês'!$A$5:$A$56,"Impostos pagos no mês (R$)",'Custos por mês'!K$5:K$56)=0,"",SUMIF('Custos por mês'!$A$5:$A$56,"Impostos pagos no mês (R$)",'Custos por mês'!K$5:K$56)) | J9: =IF(SUMIF('Custos por mês'!$A$5:$A$56,"Descontos concedidos",'Custos por mês'!K$5:K$56)=0,"",SUMIF('Custos por mês'!$A$5:$A$56,"Descontos concedidos",'Custos por mês'!K$5:K$56)) | K9: =IF(SUMIF('Custos por mês'!$A$5:$A$56,"Despesas financeiras",'Custos por mês'!K$5:K$56)=0,"",SUMIF('Custos por mês'!$A$5:$A$56,"Despesas financeiras",'Custos por mês'!K$5:K$56)) | L9: =IF(SUMIF('Custos por mês'!$A$5:$A$56,"Parcelas de dívidas pagas no mês",'Custos por mês'!K$5:K$56)=0,"",SUMIF('Custos por mês'!$A$5:$A$56,"Parcelas de dívidas pagas no mês",'Custos por mês'!K$5:K$56)) | M9: =IF(SUMIF('Custos por mês'!$A$5:$A$56,"Saldo devedor de empréstimos",'Custos por mês'!K$5:K$56)=0,"",SUMIF('Custos por mês'!$A$5:$A$56,"Saldo devedor de empréstimos",'Custos por mês'!K$5:K$56)) | N9: =IF(SUMIF('Custos por mês'!$A$5:$A$56,"Saldo de caixa no fim do mês",'Custos por mês'!K$5:K$56)=0,"",SUMIF('Custos por mês'!$A$5:$A$56,"Saldo de caixa no fim do mês",'Custos por mês'!K$5:K$56))
A10: ='Custos por mês'!L4 | B10: =IF(SUMIF('Custos por mês'!$A$5:$A$56,"Equipe administrativa e pró-labore",'Custos por mês'!L$5:L$56)=0,"",SUMIF('Custos por mês'!$A$5:$A$56,"Equipe administrativa e pró-labore",'Custos por mês'!L$5:L$56)) | C10: =IF(SUMIF('Custos por mês'!$A$5:$A$56,"Aluguel, condomínio e utilidades",'Custos por mês'!L$5:L$56)=0,"",SUMIF('Custos por mês'!$A$5:$A$56,"Aluguel, condomínio e utilidades",'Custos por mês'!L$5:L$56)) | D10: =IF(SUMIF('Custos por mês'!$A$5:$A$56,"Sistemas, marketing e outros fixos",'Custos por mês'!L$5:L$56)=0,"",SUMIF('Custos por mês'!$A$5:$A$56,"Sistemas, marketing e outros fixos",'Custos por mês'!L$5:L$56)) | E10: =IF(SUMIF('Custos por mês'!$A$5:$A$56,"Insumos e materiais",'Custos por mês'!L$5:L$56)=0,"",SUMIF('Custos por mês'!$A$5:$A$56,"Insumos e materiais",'Custos por mês'!L$5:L$56)) | F10: =IF(SUMIF('Custos por mês'!$A$5:$A$56,"Profissionais da assistência (repasse/folha)",'Custos por mês'!L$5:L$56)=0,"",SUMIF('Custos por mês'!$A$5:$A$56,"Profissionais da assistência (repasse/folha)",'Custos por mês'!L$5:L$56)) | G10: =IF(SUMIF('Custos por mês'!$A$5:$A$56,"Comissões e outros variáveis (opcional)",'Custos por mês'!L$5:L$56)=0,"",SUMIF('Custos por mês'!$A$5:$A$56,"Comissões e outros variáveis (opcional)",'Custos por mês'!L$5:L$56)) | H10: =IF(SUMIF('Custos por mês'!$A$5:$A$56,"Taxas de cartão e antecipação",'Custos por mês'!L$5:L$56)=0,"",SUMIF('Custos por mês'!$A$5:$A$56,"Taxas de cartão e antecipação",'Custos por mês'!L$5:L$56)) | I10: =IF(SUMIF('Custos por mês'!$A$5:$A$56,"Impostos pagos no mês (R$)",'Custos por mês'!L$5:L$56)=0,"",SUMIF('Custos por mês'!$A$5:$A$56,"Impostos pagos no mês (R$)",'Custos por mês'!L$5:L$56)) | J10: =IF(SUMIF('Custos por mês'!$A$5:$A$56,"Descontos concedidos",'Custos por mês'!L$5:L$56)=0,"",SUMIF('Custos por mês'!$A$5:$A$56,"Descontos concedidos",'Custos por mês'!L$5:L$56)) | K10: =IF(SUMIF('Custos por mês'!$A$5:$A$56,"Despesas financeiras",'Custos por mês'!L$5:L$56)=0,"",SUMIF('Custos por mês'!$A$5:$A$56,"Despesas financeiras",'Custos por mês'!L$5:L$56)) | L10: =IF(SUMIF('Custos por mês'!$A$5:$A$56,"Parcelas de dívidas pagas no mês",'Custos por mês'!L$5:L$56)=0,"",SUMIF('Custos por mês'!$A$5:$A$56,"Parcelas de dívidas pagas no mês",'Custos por mês'!L$5:L$56)) | M10: =IF(SUMIF('Custos por mês'!$A$5:$A$56,"Saldo devedor de empréstimos",'Custos por mês'!L$5:L$56)=0,"",SUMIF('Custos por mês'!$A$5:$A$56,"Saldo devedor de empréstimos",'Custos por mês'!L$5:L$56)) | N10: =IF(SUMIF('Custos por mês'!$A$5:$A$56,"Saldo de caixa no fim do mês",'Custos por mês'!L$5:L$56)=0,"",SUMIF('Custos por mês'!$A$5:$A$56,"Saldo de caixa no fim do mês",'Custos por mês'!L$5:L$56))
A11: ='Custos por mês'!M4 | B11: =IF(SUMIF('Custos por mês'!$A$5:$A$56,"Equipe administrativa e pró-labore",'Custos por mês'!M$5:M$56)=0,"",SUMIF('Custos por mês'!$A$5:$A$56,"Equipe administrativa e pró-labore",'Custos por mês'!M$5:M$56)) | C11: =IF(SUMIF('Custos por mês'!$A$5:$A$56,"Aluguel, condomínio e utilidades",'Custos por mês'!M$5:M$56)=0,"",SUMIF('Custos por mês'!$A$5:$A$56,"Aluguel, condomínio e utilidades",'Custos por mês'!M$5:M$56)) | D11: =IF(SUMIF('Custos por mês'!$A$5:$A$56,"Sistemas, marketing e outros fixos",'Custos por mês'!M$5:M$56)=0,"",SUMIF('Custos por mês'!$A$5:$A$56,"Sistemas, marketing e outros fixos",'Custos por mês'!M$5:M$56)) | E11: =IF(SUMIF('Custos por mês'!$A$5:$A$56,"Insumos e materiais",'Custos por mês'!M$5:M$56)=0,"",SUMIF('Custos por mês'!$A$5:$A$56,"Insumos e materiais",'Custos por mês'!M$5:M$56)) | F11: =IF(SUMIF('Custos por mês'!$A$5:$A$56,"Profissionais da assistência (repasse/folha)",'Custos por mês'!M$5:M$56)=0,"",SUMIF('Custos por mês'!$A$5:$A$56,"Profissionais da assistência (repasse/folha)",'Custos por mês'!M$5:M$56)) | G11: =IF(SUMIF('Custos por mês'!$A$5:$A$56,"Comissões e outros variáveis (opcional)",'Custos por mês'!M$5:M$56)=0,"",SUMIF('Custos por mês'!$A$5:$A$56,"Comissões e outros variáveis (opcional)",'Custos por mês'!M$5:M$56)) | H11: =IF(SUMIF('Custos por mês'!$A$5:$A$56,"Taxas de cartão e antecipação",'Custos por mês'!M$5:M$56)=0,"",SUMIF('Custos por mês'!$A$5:$A$56,"Taxas de cartão e antecipação",'Custos por mês'!M$5:M$56)) | I11: =IF(SUMIF('Custos por mês'!$A$5:$A$56,"Impostos pagos no mês (R$)",'Custos por mês'!M$5:M$56)=0,"",SUMIF('Custos por mês'!$A$5:$A$56,"Impostos pagos no mês (R$)",'Custos por mês'!M$5:M$56)) | J11: =IF(SUMIF('Custos por mês'!$A$5:$A$56,"Descontos concedidos",'Custos por mês'!M$5:M$56)=0,"",SUMIF('Custos por mês'!$A$5:$A$56,"Descontos concedidos",'Custos por mês'!M$5:M$56)) | K11: =IF(SUMIF('Custos por mês'!$A$5:$A$56,"Despesas financeiras",'Custos por mês'!M$5:M$56)=0,"",SUMIF('Custos por mês'!$A$5:$A$56,"Despesas financeiras",'Custos por mês'!M$5:M$56)) | L11: =IF(SUMIF('Custos por mês'!$A$5:$A$56,"Parcelas de dívidas pagas no mês",'Custos por mês'!M$5:M$56)=0,"",SUMIF('Custos por mês'!$A$5:$A$56,"Parcelas de dívidas pagas no mês",'Custos por mês'!M$5:M$56)) | M11: =IF(SUMIF('Custos por mês'!$A$5:$A$56,"Saldo devedor de empréstimos",'Custos por mês'!M$5:M$56)=0,"",SUMIF('Custos por mês'!$A$5:$A$56,"Saldo devedor de empréstimos",'Custos por mês'!M$5:M$56)) | N11: =IF(SUMIF('Custos por mês'!$A$5:$A$56,"Saldo de caixa no fim do mês",'Custos por mês'!M$5:M$56)=0,"",SUMIF('Custos por mês'!$A$5:$A$56,"Saldo de caixa no fim do mês",'Custos por mês'!M$5:M$56))
A12: ='Custos por mês'!N4 | B12: =IF(SUMIF('Custos por mês'!$A$5:$A$56,"Equipe administrativa e pró-labore",'Custos por mês'!N$5:N$56)=0,"",SUMIF('Custos por mês'!$A$5:$A$56,"Equipe administrativa e pró-labore",'Custos por mês'!N$5:N$56)) | C12: =IF(SUMIF('Custos por mês'!$A$5:$A$56,"Aluguel, condomínio e utilidades",'Custos por mês'!N$5:N$56)=0,"",SUMIF('Custos por mês'!$A$5:$A$56,"Aluguel, condomínio e utilidades",'Custos por mês'!N$5:N$56)) | D12: =IF(SUMIF('Custos por mês'!$A$5:$A$56,"Sistemas, marketing e outros fixos",'Custos por mês'!N$5:N$56)=0,"",SUMIF('Custos por mês'!$A$5:$A$56,"Sistemas, marketing e outros fixos",'Custos por mês'!N$5:N$56)) | E12: =IF(SUMIF('Custos por mês'!$A$5:$A$56,"Insumos e materiais",'Custos por mês'!N$5:N$56)=0,"",SUMIF('Custos por mês'!$A$5:$A$56,"Insumos e materiais",'Custos por mês'!N$5:N$56)) | F12: =IF(SUMIF('Custos por mês'!$A$5:$A$56,"Profissionais da assistência (repasse/folha)",'Custos por mês'!N$5:N$56)=0,"",SUMIF('Custos por mês'!$A$5:$A$56,"Profissionais da assistência (repasse/folha)",'Custos por mês'!N$5:N$56)) | G12: =IF(SUMIF('Custos por mês'!$A$5:$A$56,"Comissões e outros variáveis (opcional)",'Custos por mês'!N$5:N$56)=0,"",SUMIF('Custos por mês'!$A$5:$A$56,"Comissões e outros variáveis (opcional)",'Custos por mês'!N$5:N$56)) | H12: =IF(SUMIF('Custos por mês'!$A$5:$A$56,"Taxas de cartão e antecipação",'Custos por mês'!N$5:N$56)=0,"",SUMIF('Custos por mês'!$A$5:$A$56,"Taxas de cartão e antecipação",'Custos por mês'!N$5:N$56)) | I12: =IF(SUMIF('Custos por mês'!$A$5:$A$56,"Impostos pagos no mês (R$)",'Custos por mês'!N$5:N$56)=0,"",SUMIF('Custos por mês'!$A$5:$A$56,"Impostos pagos no mês (R$)",'Custos por mês'!N$5:N$56)) | J12: =IF(SUMIF('Custos por mês'!$A$5:$A$56,"Descontos concedidos",'Custos por mês'!N$5:N$56)=0,"",SUMIF('Custos por mês'!$A$5:$A$56,"Descontos concedidos",'Custos por mês'!N$5:N$56)) | K12: =IF(SUMIF('Custos por mês'!$A$5:$A$56,"Despesas financeiras",'Custos por mês'!N$5:N$56)=0,"",SUMIF('Custos por mês'!$A$5:$A$56,"Despesas financeiras",'Custos por mês'!N$5:N$56)) | L12: =IF(SUMIF('Custos por mês'!$A$5:$A$56,"Parcelas de dívidas pagas no mês",'Custos por mês'!N$5:N$56)=0,"",SUMIF('Custos por mês'!$A$5:$A$56,"Parcelas de dívidas pagas no mês",'Custos por mês'!N$5:N$56)) | M12: =IF(SUMIF('Custos por mês'!$A$5:$A$56,"Saldo devedor de empréstimos",'Custos por mês'!N$5:N$56)=0,"",SUMIF('Custos por mês'!$A$5:$A$56,"Saldo devedor de empréstimos",'Custos por mês'!N$5:N$56)) | N12: =IF(SUMIF('Custos por mês'!$A$5:$A$56,"Saldo de caixa no fim do mês",'Custos por mês'!N$5:N$56)=0,"",SUMIF('Custos por mês'!$A$5:$A$56,"Saldo de caixa no fim do mês",'Custos por mês'!N$5:N$56))
A13: ='Custos por mês'!O4 | B13: =IF(SUMIF('Custos por mês'!$A$5:$A$56,"Equipe administrativa e pró-labore",'Custos por mês'!O$5:O$56)=0,"",SUMIF('Custos por mês'!$A$5:$A$56,"Equipe administrativa e pró-labore",'Custos por mês'!O$5:O$56)) | C13: =IF(SUMIF('Custos por mês'!$A$5:$A$56,"Aluguel, condomínio e utilidades",'Custos por mês'!O$5:O$56)=0,"",SUMIF('Custos por mês'!$A$5:$A$56,"Aluguel, condomínio e utilidades",'Custos por mês'!O$5:O$56)) | D13: =IF(SUMIF('Custos por mês'!$A$5:$A$56,"Sistemas, marketing e outros fixos",'Custos por mês'!O$5:O$56)=0,"",SUMIF('Custos por mês'!$A$5:$A$56,"Sistemas, marketing e outros fixos",'Custos por mês'!O$5:O$56)) | E13: =IF(SUMIF('Custos por mês'!$A$5:$A$56,"Insumos e materiais",'Custos por mês'!O$5:O$56)=0,"",SUMIF('Custos por mês'!$A$5:$A$56,"Insumos e materiais",'Custos por mês'!O$5:O$56)) | F13: =IF(SUMIF('Custos por mês'!$A$5:$A$56,"Profissionais da assistência (repasse/folha)",'Custos por mês'!O$5:O$56)=0,"",SUMIF('Custos por mês'!$A$5:$A$56,"Profissionais da assistência (repasse/folha)",'Custos por mês'!O$5:O$56)) | G13: =IF(SUMIF('Custos por mês'!$A$5:$A$56,"Comissões e outros variáveis (opcional)",'Custos por mês'!O$5:O$56)=0,"",SUMIF('Custos por mês'!$A$5:$A$56,"Comissões e outros variáveis (opcional)",'Custos por mês'!O$5:O$56)) | H13: =IF(SUMIF('Custos por mês'!$A$5:$A$56,"Taxas de cartão e antecipação",'Custos por mês'!O$5:O$56)=0,"",SUMIF('Custos por mês'!$A$5:$A$56,"Taxas de cartão e antecipação",'Custos por mês'!O$5:O$56)) | I13: =IF(SUMIF('Custos por mês'!$A$5:$A$56,"Impostos pagos no mês (R$)",'Custos por mês'!O$5:O$56)=0,"",SUMIF('Custos por mês'!$A$5:$A$56,"Impostos pagos no mês (R$)",'Custos por mês'!O$5:O$56)) | J13: =IF(SUMIF('Custos por mês'!$A$5:$A$56,"Descontos concedidos",'Custos por mês'!O$5:O$56)=0,"",SUMIF('Custos por mês'!$A$5:$A$56,"Descontos concedidos",'Custos por mês'!O$5:O$56)) | K13: =IF(SUMIF('Custos por mês'!$A$5:$A$56,"Despesas financeiras",'Custos por mês'!O$5:O$56)=0,"",SUMIF('Custos por mês'!$A$5:$A$56,"Despesas financeiras",'Custos por mês'!O$5:O$56)) | L13: =IF(SUMIF('Custos por mês'!$A$5:$A$56,"Parcelas de dívidas pagas no mês",'Custos por mês'!O$5:O$56)=0,"",SUMIF('Custos por mês'!$A$5:$A$56,"Parcelas de dívidas pagas no mês",'Custos por mês'!O$5:O$56)) | M13: =IF(SUMIF('Custos por mês'!$A$5:$A$56,"Saldo devedor de empréstimos",'Custos por mês'!O$5:O$56)=0,"",SUMIF('Custos por mês'!$A$5:$A$56,"Saldo devedor de empréstimos",'Custos por mês'!O$5:O$56)) | N13: =IF(SUMIF('Custos por mês'!$A$5:$A$56,"Saldo de caixa no fim do mês",'Custos por mês'!O$5:O$56)=0,"",SUMIF('Custos por mês'!$A$5:$A$56,"Saldo de caixa no fim do mês",'Custos por mês'!O$5:O$56))
